example_package_tommwa/__init__.py
example_package_tommwa/example.py
example_package_tommwa-0.0.1.dist-info/LICENSE.txt
example_package_tommwa-0.0.1.dist-info/METADATA
example_package_tommwa-0.0.1.dist-info/WHEEL
example_package_tommwa-0.0.1.dist-info/top_level.txt
example_package_tommwa-0.0.1.dist-info/RECORD
