Metadata-Version: 2.1
Name: example-package-tommwa
Version: 0.0.1
Summary: A small example package
Author-email: Tommy Wallin <tommy.wallin1@gmail.com>
Classifier: Programming Language :: Python :: 3
Classifier: License :: OSI Approved :: MIT License
Classifier: Operating System :: OS Independent
Requires-Python: >=3.7
License-File: LICENSE.txt
Requires-Dist: sc2reader
